dichecker/__init__.py
dichecker/checker.py
dichecker/errors.py
dichecker/handlers/__init__.py
dichecker/handlers/any.py
dichecker/handlers/dict.py
dichecker/handlers/list.py
dichecker/handlers/literal.py
dichecker/handlers/none.py
dichecker/handlers/object.py
dichecker/handlers/typed_dict.py
dichecker/handlers/union.py
dichecker/py.typed
dichecker-6.6.6.dist-info/LICENSE
dichecker-6.6.6.dist-info/WHEEL
dichecker-6.6.6.dist-info/METADATA
dichecker-6.6.6.dist-info/RECORD
